__main__.py
kernel_daemon.py
mcp_jupyter_server_fast.py
notebook_client.py
jupyter_mcp_kernel-1.0.1.dist-info/licenses/LICENSE
jupyter_mcp_kernel-1.0.1.dist-info/METADATA
jupyter_mcp_kernel-1.0.1.dist-info/WHEEL
jupyter_mcp_kernel-1.0.1.dist-info/entry_points.txt
jupyter_mcp_kernel-1.0.1.dist-info/top_level.txt
jupyter_mcp_kernel-1.0.1.dist-info/RECORD
